{"lastUsed":1512625364461,"path":"C:\/Users\/BAChan\/Documents\/GitHub\/Java","projectCount":2,"recentFiles":[{"path":"\/AlgorithmeEX\/src\/com\/BJ\/bj6603","parentWorkspace":"C:\/Users\/BAChan\/Documents\/GitHub\/Java","name":"BJ6603.java","lastModified":1512289378961,"locationURI":"file:\/C:\/Users\/BAChan\/Documents\/GitHub\/Java\/AlgorithmeEX\/src\/com\/BJ\/bj6603\/BJ6603.java"},{"path":"\/AlgorithmeEX\/src\/com\/BJ\/bj11053","parentWorkspace":"C:\/Users\/BAChan\/Documents\/GitHub\/Java","name":"BJ11053.java","lastModified":1512372124007,"locationURI":"file:\/C:\/Users\/BAChan\/Documents\/GitHub\/Java\/AlgorithmeEX\/src\/com\/BJ\/bj11053\/BJ11053.java"},{"path":"\/AlgorithmeEX\/src\/com\/BJ\/bj11052","parentWorkspace":"C:\/Users\/BAChan\/Documents\/GitHub\/Java","name":"bj11052.java","lastModified":1512463381249,"locationURI":"file:\/C:\/Users\/BAChan\/Documents\/GitHub\/Java\/AlgorithmeEX\/src\/com\/BJ\/bj11052\/bj11052.java"},{"path":"\/AlgorithmeEX\/src\/com\/BJ\/bj2468","parentWorkspace":"C:\/Users\/BAChan\/Documents\/GitHub\/Java","name":"BJ2468.java","lastModified":1512289378961,"locationURI":"file:\/C:\/Users\/BAChan\/Documents\/GitHub\/Java\/AlgorithmeEX\/src\/com\/BJ\/bj2468\/BJ2468.java"},{"path":"\/AlgorithmeEX\/src\/com\/BJ\/bj2178","parentWorkspace":"C:\/Users\/BAChan\/Documents\/GitHub\/Java","name":"BJ2178.java","lastModified":1512289378960,"locationURI":"file:\/C:\/Users\/BAChan\/Documents\/GitHub\/Java\/AlgorithmeEX\/src\/com\/BJ\/bj2178\/BJ2178.java"},{"path":"\/AlgorithmeEX\/src\/com\/BJ\/bj9095","parentWorkspace":"C:\/Users\/BAChan\/Documents\/GitHub\/Java","name":"BJ9095.java","lastModified":1512289378961,"locationURI":"file:\/C:\/Users\/BAChan\/Documents\/GitHub\/Java\/AlgorithmeEX\/src\/com\/BJ\/bj9095\/BJ9095.java"},{"path":"\/AlgorithmeEX\/src\/com\/BJ\/bj11403","parentWorkspace":"C:\/Users\/BAChan\/Documents\/GitHub\/Java","name":"BJ11403.java","lastModified":1512289378960,"locationURI":"file:\/C:\/Users\/BAChan\/Documents\/GitHub\/Java\/AlgorithmeEX\/src\/com\/BJ\/bj11403\/BJ11403.java"},{"path":"\/AlgorithmeEX\/src\/com\/BJ\/bj1260","parentWorkspace":"C:\/Users\/BAChan\/Documents\/GitHub\/Java","name":"BJ1260.java","lastModified":1512289378960,"locationURI":"file:\/C:\/Users\/BAChan\/Documents\/GitHub\/Java\/AlgorithmeEX\/src\/com\/BJ\/bj1260\/BJ1260.java"},{"path":"\/AlgorithmeEX\/src\/com\/BJ\/bj2293","parentWorkspace":"C:\/Users\/BAChan\/Documents\/GitHub\/Java","name":"bj2293.java","lastModified":1512468095586,"locationURI":"file:\/C:\/Users\/BAChan\/Documents\/GitHub\/Java\/AlgorithmeEX\/src\/com\/BJ\/bj2293\/bj2293.java"}]}